README.md
setup.py
BpkHello/BpkHello.py
BpkHello/__init__.py
bpk_hello.egg-info/PKG-INFO
bpk_hello.egg-info/SOURCES.txt
bpk_hello.egg-info/dependency_links.txt
bpk_hello.egg-info/requires.txt
bpk_hello.egg-info/top_level.txt