Metadata-Version: 2.1
Name: bpk-hello
Version: 0.1
Summary: BPK Hello Description
Home-page: https://www.bpk.go.id/
Download-URL: https://www.bpk.go.id/
Author: deviardn
Author-email: deviardn@gmail.com
License: MIT
Project-URL: Documentation, https://packaging.python.org/tutorials/distributing-packages/
Project-URL: Funding, https://donate.pypi.org
Project-URL: Say Thanks!, http://saythanks.io/to/example
Project-URL: Source, https://github.com/pypa/sampleproject/
Project-URL: Tracker, https://github.com/pypa/sampleproject/issues
Keywords: SOME,MEANINGFULL,KEYWORDS
Classifier: Development Status :: 3 - Alpha
Classifier: Intended Audience :: Developers
Classifier: Topic :: Software Development :: Build Tools
Classifier: License :: OSI Approved :: MIT License
Classifier: Programming Language :: Python :: 3
Classifier: Programming Language :: Python :: 3.4
Classifier: Programming Language :: Python :: 3.5
Classifier: Programming Language :: Python :: 3.6
Requires-Dist: validators
Requires-Dist: beautifulsoup4
